setup.py
contentadmin/__init__.py
contentadmin/admin.py
contentadmin/models.py
contentadmin/tests.py
contentadmin/migrations/0001_initial.py
contentadmin/migrations/__init__.py
contentadmin/templatetags/__init__.py
contentadmin/templatetags/blockimage.py
contentadmin/templatetags/blocktext.py
contentadmin/templatetags/contentadmin_tags.py
contentadmin/templatetags/unusedblocks.py
django_contentadmin.egg-info/PKG-INFO
django_contentadmin.egg-info/SOURCES.txt
django_contentadmin.egg-info/dependency_links.txt
django_contentadmin.egg-info/not-zip-safe
django_contentadmin.egg-info/requires.txt
django_contentadmin.egg-info/top_level.txt