Metadata-Version: 1.0
Name: django-contentadmin
Version: 0.2.0
Summary: Templatetags that let you modify text and image directly in the admin
Home-page: https://bitbucket.org/surfeurx/django-contentadmin
Author: Amine chouki
Author-email: surfeurX@gmail.com
License: UNKNOWN
Platform: UNKNOWN
